mat3ra/__init__.py
mat3ra/periodic_table/__init__.py
mat3ra/periodic_table/bonds.py
mat3ra/periodic_table/colors.py
mat3ra/periodic_table/helpers.py
mat3ra_periodic_table-2025.12.27.post0.dist-info/licenses/LICENSE.md
mat3ra_periodic_table-2025.12.27.post0.dist-info/METADATA
mat3ra_periodic_table-2025.12.27.post0.dist-info/WHEEL
mat3ra_periodic_table-2025.12.27.post0.dist-info/top_level.txt
mat3ra_periodic_table-2025.12.27.post0.dist-info/RECORD
