Metadata-Version: 2.4
Name: mat3ra-periodic-table
Version: 2025.12.27.post0
Summary: Data for the Periodic Table of Elements
Author-email: "Exabyte Inc." <info@mat3ra.com>
Requires-Python: >=3.8
License-File: LICENSE.md
Provides-Extra: tests
Requires-Dist: pytest>=7.0; extra == "tests"
Requires-Dist: coverage[toml]>=5.3; extra == "tests"
Provides-Extra: all
Requires-Dist: mat3ra-periodic-table[tests]; extra == "all"
Dynamic: license-file
